README.md
setup.py
odd_ge/__init__.py
odd_ge/data_context.py
odd_ge/dataclasses.py
odd_ge/oddrn.py
odd_ge/settings.py
odd_ge.egg-info/PKG-INFO
odd_ge.egg-info/SOURCES.txt
odd_ge.egg-info/dependency_links.txt
odd_ge.egg-info/not-zip-safe
odd_ge.egg-info/requires.txt
odd_ge.egg-info/top_level.txt