Metadata-Version: 2.1
Name: odd-ge
Version: 0.0.1
Summary: ODD adapter to Great Expectations
Home-page: UNKNOWN
Author: Provectus ODD team
License: UNKNOWN
Keywords: odd-ge-adapter
Platform: UNKNOWN
Requires-Python: >=3.6
